aia_fairness/__init__.py
aia_fairness/config/__init__.py
aia_fairness/config/__main__.py
aia_fairness/config/default.py
aia_fairness/config/tmp_conf.py
aia_fairness/dataset_processing/$
aia_fairness/dataset_processing/__init__.py
aia_fairness/dataset_processing/config.py
aia_fairness/dataset_processing/main.py
aia_fairness/dataset_processing/metric.py
aia_fairness/dataset_processing/evaluation/__main__.py
aia_fairness/dataset_processing/fetch/__main__.py
aia_fairness/evaluation/__init__.py
aia_fairness/experimental_stack/__init__.py
aia_fairness/experimental_stack/__main__.py
aia_fairness/experimental_stack/bck/__init__.py
aia_fairness/experimental_stack/bck/__main__.py
aia_fairness/hyper_parameter_tuning/__init__.py
aia_fairness/hyper_parameter_tuning/debiasing/__init__.py
aia_fairness/hyper_parameter_tuning/debiasing/__main__.py
aia_fairness/hyper_parameter_tuning/debiasing/alpha_manager.py
aia_fairness/hyper_parameter_tuning/debiasing/alpha_optimization.py
aia_fairness/hyper_parameter_tuning/debiasing/metric.py
aia_fairness/hyper_parameter_tuning/debiasing/plot.py
aia_fairness/models/__init__.py
aia_fairness/models/attack/__init__.py
aia_fairness/models/target/__init__.py
aia_fairness/models/target/alpha.pickle
aia_fairness/models/target/debiasing.py
aia_fairness/models/target/debiasing_custom.py
aia_fairness/models/target/fairgrad.py
aia_fairness/models/target/predictors.py
aia_fairness/result/__init__.py
aia_fairness/seed/__init__.py
aia_fairness-0.3.4.dist-info/METADATA
aia_fairness-0.3.4.dist-info/WHEEL
aia_fairness-0.3.4.dist-info/licenses/LICENSE
aia_fairness-0.3.4.dist-info/RECORD
