Metadata-Version: 2.1
Name: aia_fairness
Version: 0.3.4
Summary: Various attributes inferences attacks tested against fairness enforcing mechanisms
Project-URL: Homepage, https://gitlab.inria.fr/jaalmoes/aia_fairness
Project-URL: Bug Tracker, https://gitlab.inria.fr/jaalmoes/aia_fairness/issues
Author: Vasisht Duddu
Author-email: Jan Aalmoes <jan.aalmoes@protonmail.com>
License-File: LICENSE
Classifier: License :: OSI Approved :: GNU General Public License v3 or later (GPLv3+)
Classifier: Operating System :: OS Independent
Classifier: Programming Language :: Python :: 3
Requires-Python: >=3.7
Requires-Dist: fairgrad
Requires-Dist: fairlearn
Requires-Dist: folktables
Requires-Dist: kaggle
Requires-Dist: matplotlib
Requires-Dist: pillow
Requires-Dist: requests
Requires-Dist: scikit-image
Requires-Dist: scikit-learn
Requires-Dist: silence-tensorflow
Requires-Dist: tensorflow
Requires-Dist: torch
Requires-Dist: torchvision
Requires-Dist: ucimlrepo
Requires-Dist: wget
